LICENSE
MANIFEST.in
README.md
scrapy.cfg
setup.cfg
setup.py
lich_scrapy_random_useragent/__init__.py
lich_scrapy_random_useragent/errors.py
lich_scrapy_random_useragent/fakeUerAgent.py
lich_scrapy_random_useragent/items.py
lich_scrapy_random_useragent/middlewares.py
lich_scrapy_random_useragent/pipelines.py
lich_scrapy_random_useragent/settings.py
lich_scrapy_random_useragent/utils.py
lich_scrapy_random_useragent.egg-info/PKG-INFO
lich_scrapy_random_useragent.egg-info/SOURCES.txt
lich_scrapy_random_useragent.egg-info/dependency_links.txt
lich_scrapy_random_useragent.egg-info/not-zip-safe
lich_scrapy_random_useragent.egg-info/requires.txt
lich_scrapy_random_useragent.egg-info/top_level.txt
lich_scrapy_random_useragent/spiders/__init__.py
requirements/requirements-lint.txt
requirements/requirements-test.txt
requirements/requirements.txt
tests/__init__.py
tests/test_scrapy_check.py